<annotation>
	<folder>001759_05_01</folder>
	<filename>029_Original_c001759_05_01.png</filename>
	<path>C:\Users\Eli Flores\Desktop\Tesis\Code\KeySlices\Key_slices\Kidney key slices\DONE\001759_05_01\029_Original_c001759_05_01.png</path>
	<source>
		<database>Unknown</database>
	</source>
	<size>
		<width>512</width>
		<height>512</height>
		<depth>1</depth>
	</size>
	<segmented>0</segmented>
	<object>
		<name>Lesion</name>
		<pose>Unspecified</pose>
		<truncated>0</truncated>
		<difficult>0</difficult>
		<bndbox>
			<xmin>130</xmin>
			<ymin>251</ymin>
			<xmax>222</xmax>
			<ymax>349</ymax>
		</bndbox>
	</object>
</annotation>
