<annotation>
	<folder>002074_02_02</folder>
	<filename>332_Erosion_c002074_02_02.png</filename>
	<path>C:\Users\Eli Flores\Desktop\Tesis\Code\KeySlices\Key_slices\Kidney key slices\DONE\002074_02_02\332_Erosion_c002074_02_02.png</path>
	<source>
		<database>Unknown</database>
	</source>
	<size>
		<width>512</width>
		<height>512</height>
		<depth>1</depth>
	</size>
	<segmented>0</segmented>
	<object>
		<name>Lesion</name>
		<pose>Unspecified</pose>
		<truncated>0</truncated>
		<difficult>0</difficult>
		<bndbox>
			<xmin>177</xmin>
			<ymin>300</ymin>
			<xmax>199</xmax>
			<ymax>326</ymax>
		</bndbox>
	</object>
</annotation>
